harmony_transaction_generator/__init__.py
harmony_transaction_generator/_version.py
harmony_transaction_generator/account_manager.py
harmony_transaction_generator/analysis.py
harmony_transaction_generator/common.py
harmony_transaction_generator/fund.py
harmony_transaction_generator/generator.py
harmony_transaction_generator-20.1.48.dist-info/LICENSE.txt
harmony_transaction_generator-20.1.48.dist-info/METADATA
harmony_transaction_generator-20.1.48.dist-info/WHEEL
harmony_transaction_generator-20.1.48.dist-info/top_level.txt
harmony_transaction_generator-20.1.48.dist-info/RECORD
