Metadata-Version: 2.1
Name: harmony-transaction-generator
Version: 20.1.48
Summary: A transaction generator for the Harmony blockchain
Home-page: http://harmony.one/
Author: Daniel Van Der Maden
Author-email: daniel@harmony.one
License: UNKNOWN
Keywords: Harmony,blockchain,protocol
Platform: UNKNOWN
Classifier: Development Status :: 3 - Alpha
Classifier: Intended Audience :: Developers
Classifier: Topic :: Software Development :: Build Tools
Classifier: Programming Language :: Python :: 3.6
Classifier: Programming Language :: Python :: 3.7
Classifier: Programming Language :: Python :: 3.8
Requires-Dist: pyhmy
Requires-Dist: pytest
Requires-Dist: pytest-ordering
Requires-Dist: incremental
Requires-Dist: click
Requires-Dist: twisted
Requires-Dist: requests
Requires-Dist: pexpect
